{
  "name": "Roger Hampton",
  "age": 19,
  "address": {
    "street": "Ucuwi Point",
    "city": "Niggufha",
    "state": "MO",
    "zip": "14919"
  },
  "contact": {
    "phone": "(711) 783-3087",
    "servicePhone": "800183958"
  },
  "birthday": "1991-09-15T07:36:43.581Z",
  "ip": "30.228.174.116",
  "foo": "bar",
  "profile": {
    "about": "Sutpurim cucezvu logwiwen mab idici ube sistak ituuhom juzot ubimicu iduca telasoro zardij nuuhehe su. Vi pabdotjav gopnu ojeweku muugi mu sel ja irojel towji itu gaso babdupfa welow fawu eba. Geko luk milhuvoc neod ofhu ga awepidit li ewlig fuacih zah memeju zugjisja ru tucuhdi af mahahu agefkag. Za ozwu pokit fa el sabiake liep oz puma kafufe wadzog upiwavcu omva mumibupem jemkosse. Monmito amim lajnojuz iheho subop oz awado hu fopan wuczawhoh zathuzci lolzuv gomhezof puewoz me pu mevcir naeta. Wegewun veewazos nicdeboh muzhamod kotuba govogol zi redifcaw fepcizaf ze lod lo juftidme vasez dir fu wiazofev.",
    "bio": "Bunudibul sehuwaga tov nocalge larka rajcullow kikek vecdukga de wisu tufjak bav veuzzij. Re azusipki uravib irvit henuwes pak kiwco tidsecvo bo vuditez iz cievfus minodag. Wegabnu ejosuj tanuznuf ihura ifcane hit kohvihe ocoev tabuhup dig fesipu ovugugil nas buifvu. Rokilge iha ge nod veabuco muvvoj bis ebsom oti webum hukoscuv osin telhuc sen inoadaov cuf paf burasu. Vedvic fismuwwif geb vuc lu reozi gaded ceohomoz vuzsed ba zomah law. Wupdutew mom hog uj sofbab gi hoele socevpi codi ed wagbat kesezli ijaperoke ju dosizpe hekalcu."
  },
  "apiKey": "cb2d6a5bb014b8086a63aa62ecd9a097196cd4cc353c4eb4aa2b366bd92d6a31",
  "currency": {
    "code": "SBD",
    "name": "Solomon Islands Dollar"
  }
}