{
  "name": "Emma Hunt",
  "age": 23,
  "address": {
    "street": "Tozuke Junction",
    "city": "Howickuf",
    "state": "RI",
    "zip": "26514"
  },
  "contact": {
    "phone": "(352) 916-7469",
    "servicePhone": "800752646"
  },
  "birthday": "2004-12-11T05:55:17.561Z",
  "ip": "41.89.189.16",
  "foo": "bar",
  "profile": {
    "about": "Vulaev uv zu nu paztodbo eracep sujlecoz anuas munjuzis jom sodlub fughagkos nev voiwzov buuhipej. Voocupa nohakokoz ol gadoz wef wovgizaka juc vogke gubom dun zioho biijbu vi we mogagbil jesgi. Oke bahbook edatigwi os fuloflu de mu arji vahihzo bihic rawmi uh buf kabuha. Pil puvamido femuk fo depbe di wupasreh ozofioc vo kuok sek rum binpal korerse fur ase nov. Jesgawca coc ziz tajoes zigvuta ovevug tungopda akjovi odcan terhosi gi ne kuf nemovu ri. Hevesila ma ipi ceefa ol vim divohi lapzef napu nez belo ad tenulfin kaav eleatcu ulbeh dalugis wafefva.",
    "bio": "Ugjuve kij oja zewcal okmi afbu gil fop funzohki uz wivlad ef nuwfow muipmet mevij hilvotcej. Ijuavo kolku puovo orazati ho nul vieki lewko zeab ufo junodgev ugaipi sejipolu jo. Ka uzocic demekoje nekila mibavim babed cos juul caeha fac dupmondaf no zah. Ci ujwibce nolte serduned mus niv jo gej zuri aflilga aplur wi gelnehgev soneuli."
  },
  "apiKey": "f7e362a05b38bee910e73dc239bd71e2b4a4bffa337d0021a4d2fd00071c85e5",
  "currency": {
    "code": "CRC",
    "name": "Costa Rica Colon"
  }
}