{
  "name": "Sophia Wallace",
  "age": 29,
  "address": {
    "street": "Cajbij Heights",
    "city": "Nehive",
    "state": "HI",
    "zip": "38915"
  },
  "contact": {
    "phone": "(937) 243-1241",
    "servicePhone": "800943716"
  },
  "birthday": "1998-07-03T07:14:34.373Z",
  "ip": "223.249.22.177",
  "foo": "bar",
  "profile": {
    "about": "Gu lufubmo coibiki pil sodnosrer ca hu naav muphal teepe bapme om. Zibuf geiludu ge cag apelumo iwiovoasi zigrewar ikomucsiz cinipo edmihmar wahep terze dafe lokab utelases fohseva vitrunah. Ho kajzekov wuvaze nej uv rulcurek if aha tovuk ba wezur ufidu. Ipi eci mecieb jer otoil mulal leceb poj bahizzuj ragbudme hu pahgujuz jib ewa mipzan. Po pih muipo cad ozoabupe desvug usihu hi citfi redirez gu rulpef. Kiude golewnu hab fifmom wu icza do noti laczebo rojev cek kuezatag jek votjow pimbapeva nuzjuc. Cahtoasa uw utiral mobaaw jerzeb ipi rajtaru sogeczo up ziwit mirtum dihekid imsi da rozkid podedji lomdejak.",
    "bio": "Ol toldama ci zise ta as zawcefkez wiumutu jef beome jowale nim af jadmewen suz. Latjari kafobura kedeub lepiw wo jicose iwa poc gapese uheneb edoehe ul nozanav bej pajhasene. Ecotet ocvomu gar vuw diiheepi gevcuf oda dirmelehe oru gesaz miiz zuri dehuhac. Nahjuhaw fuzedu sajibeb buufeku haja abasbu jov okode nebatujep etefu or mihieg huobi domkavi tadifal muhfoma gabjafas. Lujapi jejeki ewuvor ula lenawe li wol lu hi sum izoba fuwbidga juw un sak. Ub sikep co ir ericer eca va liogo lotozula onobodep monecda bow sina."
  },
  "apiKey": "39071c9e398c8b6da39045b7f45c3257e4e34ace53fe333e636bf175829a4299",
  "currency": {
    "code": "TZS",
    "name": "Tanzania Shilling"
  }
}