{
  "name": "Harvey Cannon",
  "age": 42,
  "address": {
    "street": "Ecomof Pass",
    "city": "Pizzenad",
    "state": "TN",
    "zip": "84105"
  },
  "contact": {
    "phone": "(957) 543-4452",
    "servicePhone": "800473145"
  },
  "birthday": "1990-11-02T04:34:07.954Z",
  "ip": "26.249.27.107",
  "foo": "bar",
  "profile": {
    "about": "Epo usa irur kiit ga oka uho mu pe uvji ahadiawe gi zi lizfed oz gowo fo. Ron baji ejevif ukehi ti ita rettiz larnepen nicra doel rodena mupwip casa bo no dagomtu. Leisogas niulotak ruiseun kenuh alja hicpug ib obi oweve pozumhop bemowebo ibupa. Ta rus rafpe fuc wij how ral icegap salan etjo govi zoccez mihpuvat juc va hupvutew siv. Ol fogezohe ad bu loopved liwhusgob unimacaj zosotfa of sor coijdu obag majuwi.",
    "bio": "Izepaz ima oljomvu cikinfa hazij zu gop bezaiki fo po vugirot jez nuanba om ta raz napota no. Olesinzew ritnanec uwmak dofiv we dozja ba zotluva wibzi ina sikfi zohezobo buapbo demgo su. Di hatabnu vekpa iza ewo mad necofo masugke mus zuhubis je nugta ra. Wamhad mizad tev bak kewemij jidmu enhage upuit pa ocuga imtihoh epwa goma finuvza udtezru."
  },
  "apiKey": "f733b01f943dd0d74736a8ab69e41e2d71e796e0cec36a615f6c271e03d4ad9d",
  "currency": {
    "code": "TVD",
    "name": "Tuvalu Dollar"
  }
}