{
  "name": "Sadie Carlson",
  "age": 64,
  "address": {
    "street": "Napfev Pass",
    "city": "Evdawok",
    "state": "IL",
    "zip": "70260"
  },
  "contact": {
    "phone": "(659) 627-5270",
    "servicePhone": "800813846"
  },
  "birthday": "2005-03-24T02:15:29.031Z",
  "ip": "46.63.174.151",
  "foo": "bar",
  "profile": {
    "about": "Vefge kemitef mocatab ke foczunjor vumaw be udi nava uzoip erenitov bajer ku oc ut cifgep hebka hezlufuj. Fo gofjop fatmew jasikut sinpova ponzo wihwujip zowiglog vuppowov vo iztahofo debper weneij zujwajiw rabho pitga ukueh lafsosob. Pimu of if hob caudeko vesfoma sotziwolu ba kepef cuzdaffet fegjoco ol fibmew nu. Naufo jedov diz fuz cear duc aciefpuf didmi visubu depsa vu julral sok liwu nurru.",
    "bio": "Mu gu co taw zamwab upe zeg wowzavug zif noz wo ni wenonsor tupekahi. Davut lo defegbaj deg fusu jub tudes ihomoj vocbendeh dehupbo big wugvirkof makoj lo bizoj ehsusos hinapu. Wis talap zebinebi ciobzu ikukaiw baj obvohob aw pofhekni ece zuz datke seze pofuzmil wozturlim ewjah."
  },
  "apiKey": "8467bb5506d06b32e75d3db05d5662acba2ce246a03400db7f4d1c3ed7f29cfe",
  "currency": {
    "code": "MRO",
    "name": "Mauritania Ouguiya"
  }
}